TMP1075/__init__.py
TMP1075/py.typed
TMP1075-0.2.2.dist-info/LICENSE
TMP1075-0.2.2.dist-info/METADATA
TMP1075-0.2.2.dist-info/WHEEL
TMP1075-0.2.2.dist-info/top_level.txt
TMP1075-0.2.2.dist-info/RECORD
