Metadata-Version: 2.1
Name: TMP1075
Version: 0.2.2
Summary: A python wrapper for interacting with the TMP1075
Home-page: https://github.com/Pioreactor/TMP1075
Author: Cam Davidson-Pilon
Author-email: cam@pioreactor.com
License: MIT
Requires-Python: >=3.6
License-File: LICENSE
Requires-Dist: Adafruit-Blinka
Requires-Dist: adafruit-circuitpython-busdevice
